pyece/__init__.py
pyece/__init__.pyi
pyece/__version__.py
pyece/__version__.pyi
pyece/box.py
pyece/box.pyi
pyece/im.py
pyece/im.pyi
pyece/py.typed
pyece/core/__init__.py
pyece/core/__init__.pyi
pyece/core/typing.py
pyece/core/typing.pyi
pyece/core/math/__init__.py
pyece/core/math/__init__.pyi
pyece/core/math/rotate.py
pyece/core/math/rotate.pyi
pyece/core/property/__init__.py
pyece/core/property/__init__.pyi
pyece/core/property/base.py
pyece/core/property/base.pyi
pyece/core/property/point.py
pyece/core/property/point.pyi
pyece/core/property/pointcloud.py
pyece/core/property/pointcloud.pyi
pyece-0.1.0.dist-info/LICENSE
pyece-0.1.0.dist-info/METADATA
pyece-0.1.0.dist-info/WHEEL
pyece-0.1.0.dist-info/top_level.txt
pyece-0.1.0.dist-info/RECORD
